opennsfw_standalone/__init__.py
opennsfw_standalone/__main__.py
opennsfw_standalone/inference_runner.py
opennsfw_standalone/open-nsfw.onnx
tests/__init__.py
tests/test_inference_runner.py
opennsfw_standalone-0.0.6.dist-info/LICENSE
opennsfw_standalone-0.0.6.dist-info/METADATA
opennsfw_standalone-0.0.6.dist-info/WHEEL
opennsfw_standalone-0.0.6.dist-info/top_level.txt
opennsfw_standalone-0.0.6.dist-info/RECORD
