Metadata-Version: 2.1
Name: opennsfw-standalone
Version: 0.0.6
Summary: Stand-alone wrapper for Yahoo's OpenNSFW model using ONNX.
Home-page: https://github.com/SectorLabs/opennsfw-standalone
Author: Sector Labs
Author-email: open-source@sectorlabs.ro
License: MIT License
Keywords: nsfw,machine learning,opennsfw,yahoo
Platform: UNKNOWN
Classifier: Intended Audience :: Developers
Classifier: License :: OSI Approved :: MIT License
Classifier: Operating System :: OS Independent
Classifier: Programming Language :: Python
Classifier: Programming Language :: Python :: 3.8
Requires-Python: >=3.8
Requires-Dist: Pillow (<9.0.0,>=8.2.0)
Requires-Dist: onnxruntime (<2.0.0,>=1.7.0)
Provides-Extra: analysis
Requires-Dist: black (==20.8b1) ; extra == 'analysis'
Requires-Dist: flake8 (==3.9.0) ; extra == 'analysis'
Requires-Dist: autoflake (==1.4) ; extra == 'analysis'
Requires-Dist: autopep8 (==1.5.5) ; extra == 'analysis'
Requires-Dist: isort (==5.7.0) ; extra == 'analysis'
Requires-Dist: docformatter (==1.4) ; extra == 'analysis'
Provides-Extra: test
Requires-Dist: pytest (==6.2.2) ; extra == 'test'
Requires-Dist: pytest-cov (==2.11.1) ; extra == 'test'
Requires-Dist: tox (==3.23.0) ; extra == 'test'
